thread_queue.py
thread_queue-0.2.3.dist-info/top_level.txt
thread_queue-0.2.3.dist-info/METADATA
thread_queue-0.2.3.dist-info/DESCRIPTION.rst
thread_queue-0.2.3.dist-info/metadata.json
thread_queue-0.2.3.dist-info/WHEEL
thread_queue-0.2.3.dist-info/RECORD
