Metadata-Version: 1.1
Name: thread-queue
Version: 0.2.3
Summary: A tool to queue tasks and execute them on a fixed number of threads
Home-page: https://github.com/timmartin19/thread_queue
Author: Tim Martin
Author-email: tim@timmartin.me
License: MIT license
Keywords: thread_queue
Platform: UNKNOWN
Classifier: Development Status :: 2 - Pre-Alpha
Classifier: Intended Audience :: Developers
Classifier: License :: OSI Approved :: MIT License
Classifier: Natural Language :: English
Classifier: Programming Language :: Python :: 2
Classifier: Programming Language :: Python :: 2.6
Classifier: Programming Language :: Python :: 2.7
Classifier: Programming Language :: Python :: 3
Classifier: Programming Language :: Python :: 3.3
Classifier: Programming Language :: Python :: 3.4
Classifier: Programming Language :: Python :: 3.5
